setup.cfg
setup.py
awscli_keyring/__init__.py
awscli_keyring/commands.py
awscli_keyring/persistence.py
awscli_keyring/session.py
awscli_keyring.egg-info/PKG-INFO
awscli_keyring.egg-info/SOURCES.txt
awscli_keyring.egg-info/dependency_links.txt
awscli_keyring.egg-info/requires.txt
awscli_keyring.egg-info/top_level.txt