Metadata-Version: 1.1
Name: awscli-keyring
Version: 0.1.2
Summary: AWS command line credentials from OS X Keychain and other keyrings.
Home-page: https://github.com/sj26/awscli-keyring
Author: Samuel Cochran
Author-email: sj26@sj26.com
License: MIT
Platform: UNKNOWN
Classifier: Development Status :: 2 - Pre-Alpha
Classifier: Intended Audience :: Developers
Classifier: Intended Audience :: System Administrators
Classifier: Natural Language :: English
Classifier: License :: OSI Approved :: MIT License
Classifier: Programming Language :: Python
